{
  "SlotKey": "51.5E",
  "Transponders": [
    {
      "FrequencyMHz": 3614,
      "Polarization": "R",
      "SymbolRateKs": 2607,
      "Fec": "5/6",
      "Standard": "DVB-S",
      "Modulation": "QPSK",
      "Channels": [
        {
          "Name": "OBN Gaammee",
          "Package": "none",
          "Languages": [],
          "Type": "TV",
          "IsFta": true
        }
      ]
    },
    {
      "FrequencyMHz": 3624,
      "Polarization": "R",
      "SymbolRateKs": 4810,
      "Fec": "5/6",
      "Standard": "DVB-S",
      "Modulation": "QPSK",
      "Channels": []
    },
    {
      "FrequencyMHz": 3634,
      "Polarization": "R",
      "SymbolRateKs": 4810,
      "Fec": "5/6",
      "Standard": "DVB-S",
      "Modulation": "QPSK",
      "Channels": [
        {
          "Name": "OBN HD (Oromia)",
          "Package": "none",
          "Languages": [],
          "Type": "TV",
          "IsFta": true
        }
      ]
    },
    {
      "FrequencyMHz": 3639,
      "Polarization": "R",
      "SymbolRateKs": 2275,
      "Fec": "3/4",
      "Standard": "DVB-S2",
      "Modulation": "8PSK",
      "Channels": []
    },
    {
      "FrequencyMHz": 3645,
      "Polarization": "R",
      "SymbolRateKs": 4915,
      "Fec": "5/6",
      "Standard": "DVB-S",
      "Modulation": "QPSK",
      "Channels": [
        {
          "Name": "South TV Ethiopia",
          "Package": "TandbergTV",
          "Languages": [
            "amh"
          ],
          "Type": "TV",
          "IsFta": true
        }
      ]
    },
    {
      "FrequencyMHz": 3694,
      "Polarization": "R",
      "SymbolRateKs": 2000,
      "Fec": "5/6",
      "Standard": "DVB-S2",
      "Modulation": "8PSK",
      "Channels": []
    },
    {
      "FrequencyMHz": 3706,
      "Polarization": "R",
      "SymbolRateKs": 17950,
      "Fec": "3/4",
      "Standard": "DVB-S2",
      "Modulation": "8PSK",
      "Channels": [
        {
          "Name": "ETV News",
          "Package": "Gigacom",
          "Languages": [
            "amh"
          ],
          "Type": "TV",
          "IsFta": true
        },
        {
          "Name": "ETV Entertainment",
          "Package": "Gigacom",
          "Languages": [
            "amh"
          ],
          "Type": "TV",
          "IsFta": true
        },
        {
          "Name": "ETV Languages",
          "Package": "Gigacom",
          "Languages": [
            "amh"
          ],
          "Type": "TV",
          "IsFta": true
        },
        {
          "Name": "ETV Sport",
          "Package": "Gigacom",
          "Languages": [
            "amh"
          ],
          "Type": "TV",
          "IsFta": true
        },
        {
          "Name": "ETH National Radio TV",
          "Package": "Gigacom",
          "Languages": [
            "amh"
          ],
          "Type": "TV",
          "IsFta": true
        },
        {
          "Name": "ETH FM97 1 TV",
          "Package": "Gigacom",
          "Languages": [
            "amh"
          ],
          "Type": "TV",
          "IsFta": true
        },
        {
          "Name": "ETV FM 97 1",
          "Package": "gigacom",
          "Languages": [
            "amh"
          ],
          "Type": "Radio",
          "IsFta": true
        },
        {
          "Name": "ETV FM 104 7",
          "Package": "Gigacom",
          "Languages": [
            "amh"
          ],
          "Type": "Radio",
          "IsFta": true
        },
        {
          "Name": "ETV External Radio",
          "Package": "Gigacom",
          "Languages": [
            "amh"
          ],
          "Type": "Radio",
          "IsFta": true
        },
        {
          "Name": "ETV National Radio",
          "Package": "Gigacom",
          "Languages": [
            "amh"
          ],
          "Type": "Radio",
          "IsFta": true
        }
      ]
    },
    {
      "FrequencyMHz": 3755,
      "Polarization": "R",
      "SymbolRateKs": 1250,
      "Fec": "2/3",
      "Standard": "DVB-S2",
      "Modulation": "8PSK",
      "Channels": []
    },
    {
      "FrequencyMHz": 11010,
      "Polarization": "V",
      "SymbolRateKs": 30000,
      "Fec": "3/4",
      "Standard": "DVB-S2",
      "Modulation": "8PSK",
      "Channels": []
    },
    {
      "FrequencyMHz": 11089,
      "Polarization": "H",
      "SymbolRateKs": 35000,
      "Fec": "2/3",
      "Standard": "DVB-S2",
      "Modulation": "8PSK",
      "Channels": []
    },
    {
      "FrequencyMHz": 11130,
      "Polarization": "V",
      "SymbolRateKs": 30000,
      "Fec": "3/4",
      "Standard": "DVB-S2",
      "Modulation": "8PSK",
      "Channels": []
    },
    {
      "FrequencyMHz": 11170,
      "Polarization": "V",
      "SymbolRateKs": 30000,
      "Fec": "3/4",
      "Standard": "DVB-S2",
      "Modulation": "8PSK",
      "Channels": []
    },
    {
      "FrequencyMHz": 11230,
      "Polarization": "H",
      "SymbolRateKs": 45000,
      "Fec": "8/9",
      "Standard": "DVB-S2",
      "Modulation": "8PSK",
      "Channels": []
    },
    {
      "FrequencyMHz": 11250,
      "Polarization": "H",
      "SymbolRateKs": 10830,
      "Fec": "3/4",
      "Standard": "DVB-S2",
      "Modulation": "8PSK",
      "Channels": [
        {
          "Name": "Belarus 24 HD",
          "Package": "Harmonic",
          "Languages": [
            "rus"
          ],
          "Type": "TV",
          "IsFta": true
        }
      ]
    },
    {
      "FrequencyMHz": 11290,
      "Polarization": "H",
      "SymbolRateKs": 45000,
      "Fec": "3/4",
      "Standard": "DVB-S2",
      "Modulation": "8PSK",
      "Channels": [
        {
          "Name": "Kto est Kto",
          "Package": "Belintersat",
          "Languages": [],
          "Type": "TV",
          "IsFta": false
        },
        {
          "Name": "Ryzhiy",
          "Package": "Belintersat",
          "Languages": [
            "rus"
          ],
          "Type": "TV",
          "IsFta": false
        },
        {
          "Name": "Malysh",
          "Package": "Belintersat",
          "Languages": [
            "rus"
          ],
          "Type": "TV",
          "IsFta": false
        },
        {
          "Name": "Europa Plus TV",
          "Package": "Belintersat",
          "Languages": [
            "rus"
          ],
          "Type": "TV",
          "IsFta": false
        },
        {
          "Name": "365 dnei TV",
          "Package": "Belintersat",
          "Languages": [
            "rus"
          ],
          "Type": "TV",
          "IsFta": false
        },
        {
          "Name": "Tochka.RF",
          "Package": "Belintersat",
          "Languages": [
            "rus"
          ],
          "Type": "TV",
          "IsFta": false
        },
        {
          "Name": "Ocean TV",
          "Package": "Belintersat",
          "Languages": [
            "rus"
          ],
          "Type": "TV",
          "IsFta": false
        },
        {
          "Name": "Muzhskoy",
          "Package": "Belintersat",
          "Languages": [
            "rus"
          ],
          "Type": "TV",
          "IsFta": false
        },
        {
          "Name": "NTV\u002B Kinohit",
          "Package": "Belintersat",
          "Languages": [
            "rus"
          ],
          "Type": "TV",
          "IsFta": false
        },
        {
          "Name": "Kinomix",
          "Package": "Belintersat",
          "Languages": [
            "rus"
          ],
          "Type": "TV",
          "IsFta": false
        },
        {
          "Name": "Kinopremiera",
          "Package": "Belintersat",
          "Languages": [
            "rus"
          ],
          "Type": "TV",
          "IsFta": false
        },
        {
          "Name": "Nashe Novoe Kino",
          "Package": "Belintersat",
          "Languages": [],
          "Type": "TV",
          "IsFta": false
        },
        {
          "Name": "Kinosemia",
          "Package": "Belintersat",
          "Languages": [
            "rus"
          ],
          "Type": "TV",
          "IsFta": false
        },
        {
          "Name": "Kinokomedia",
          "Package": "Belintersat",
          "Languages": [
            "rus"
          ],
          "Type": "TV",
          "IsFta": false
        },
        {
          "Name": "Kinosvidania",
          "Package": "Belintersat",
          "Languages": [
            "rus"
          ],
          "Type": "TV",
          "IsFta": false
        },
        {
          "Name": "Mujskoe Kino HD",
          "Package": "Belintersat",
          "Languages": [
            "rus"
          ],
          "Type": "TV",
          "IsFta": false
        },
        {
          "Name": "Indijskoe Kino",
          "Package": "Belintersat",
          "Languages": [
            "rus"
          ],
          "Type": "TV",
          "IsFta": false
        },
        {
          "Name": "Rodnoe Kino",
          "Package": "Belintersat",
          "Languages": [
            "rus"
          ],
          "Type": "TV",
          "IsFta": false
        },
        {
          "Name": "Kinoserija",
          "Package": "Belintersat",
          "Languages": [
            "rus"
          ],
          "Type": "TV",
          "IsFta": false
        },
        {
          "Name": "Kuhnya TV",
          "Package": "Belintersat",
          "Languages": [
            "rus"
          ],
          "Type": "TV",
          "IsFta": false
        },
        {
          "Name": "Lya Minor",
          "Package": "Belintersat",
          "Languages": [
            "rus"
          ],
          "Type": "TV",
          "IsFta": false
        },
        {
          "Name": "Tayny Galaktiki",
          "Package": "Belintersat",
          "Languages": [
            "rus"
          ],
          "Type": "TV",
          "IsFta": false
        },
        {
          "Name": "Perviy Kosmicheskij HD",
          "Package": "Belintersat",
          "Languages": [
            "rus"
          ],
          "Type": "TV",
          "IsFta": false
        },
        {
          "Name": "Animal Family",
          "Package": "Belintersat",
          "Languages": [
            "rus"
          ],
          "Type": "TV",
          "IsFta": false
        },
        {
          "Name": "Teleputeshestviya HD",
          "Package": "Belintersat",
          "Languages": [
            "rus"
          ],
          "Type": "TV",
          "IsFta": false
        },
        {
          "Name": "Arsenal",
          "Package": "Belintersat",
          "Languages": [
            "rus"
          ],
          "Type": "TV",
          "IsFta": false
        },
        {
          "Name": "KVN",
          "Package": "Belintersat",
          "Languages": [
            "rus"
          ],
          "Type": "TV",
          "IsFta": false
        },
        {
          "Name": "Telekanal Futbol HD",
          "Package": "Belintersat",
          "Languages": [
            "rus"
          ],
          "Type": "TV",
          "IsFta": false
        },
        {
          "Name": "KHL Prime HD",
          "Package": "Belintersat",
          "Languages": [
            "rus"
          ],
          "Type": "TV",
          "IsFta": false
        },
        {
          "Name": "Auto Plus (Russia)",
          "Package": "Belintersat",
          "Languages": [
            "rus"
          ],
          "Type": "TV",
          "IsFta": false
        },
        {
          "Name": "Zagorodnaya Zhizn",
          "Package": "Belintersat",
          "Languages": [
            "rus"
          ],
          "Type": "TV",
          "IsFta": false
        },
        {
          "Name": "Ohota \u0026 Rybalka",
          "Package": "Belintersat",
          "Languages": [
            "rus"
          ],
          "Type": "TV",
          "IsFta": false
        },
        {
          "Name": "Music One - Ru TV",
          "Package": "Belintersat",
          "Languages": [
            "rus"
          ],
          "Type": "TV",
          "IsFta": false
        },
        {
          "Name": "Plus",
          "Package": "Belintersat",
          "Languages": [
            "rus"
          ],
          "Type": "TV",
          "IsFta": false
        },
        {
          "Name": "Viju TV1000",
          "Package": "Belintersat",
          "Languages": [
            "rus"
          ],
          "Type": "TV",
          "IsFta": false
        },
        {
          "Name": "TV 1000 Russkoe Kino",
          "Package": "Belintersat",
          "Languages": [
            "rus"
          ],
          "Type": "TV",
          "IsFta": false
        },
        {
          "Name": "Viju TV1000 action",
          "Package": "Belintersat",
          "Languages": [
            "rus"
          ],
          "Type": "TV",
          "IsFta": false
        },
        {
          "Name": "Viju Explore",
          "Package": "Belintersat",
          "Languages": [
            "rus"
          ],
          "Type": "TV",
          "IsFta": false
        },
        {
          "Name": "Viju History",
          "Package": "Belintersat",
          "Languages": [
            "rus"
          ],
          "Type": "TV",
          "IsFta": false
        },
        {
          "Name": "Viju Nature",
          "Package": "Belintersat",
          "Languages": [
            "rus"
          ],
          "Type": "TV",
          "IsFta": false
        },
        {
          "Name": "Viju Serial",
          "Package": "Belintersat",
          "Languages": [
            "rus"
          ],
          "Type": "TV",
          "IsFta": false
        },
        {
          "Name": "TEST 24",
          "Package": "Belintersat",
          "Languages": [
            "rus"
          ],
          "Type": "Unknown",
          "IsFta": false
        },
        {
          "Name": "TEST 24",
          "Package": "Belintersat",
          "Languages": [
            "rus"
          ],
          "Type": "Unknown",
          "IsFta": false
        },
        {
          "Name": "TEST 24",
          "Package": "Belintersat",
          "Languages": [
            "rus"
          ],
          "Type": "Unknown",
          "IsFta": false
        },
        {
          "Name": "TEST5",
          "Package": "Belintersat",
          "Languages": [
            "rus"
          ],
          "Type": "Unknown",
          "IsFta": false
        },
        {
          "Name": "TEST5",
          "Package": "Belintersat",
          "Languages": [
            "rus"
          ],
          "Type": "Unknown",
          "IsFta": false
        },
        {
          "Name": "TEST5",
          "Package": "Belintersat",
          "Languages": [
            "rus"
          ],
          "Type": "Unknown",
          "IsFta": false
        }
      ]
    },
    {
      "FrequencyMHz": 11350,
      "Polarization": "H",
      "SymbolRateKs": 45000,
      "Fec": "3/4",
      "Standard": "DVB-S2",
      "Modulation": "8PSK",
      "Channels": [
        {
          "Name": "Belarus 1",
          "Package": "Belintersat",
          "Languages": [
            "rus"
          ],
          "Type": "Unknown",
          "IsFta": false
        },
        {
          "Name": "ONT",
          "Package": "Belintersat",
          "Languages": [
            "rus"
          ],
          "Type": "Unknown",
          "IsFta": false
        },
        {
          "Name": "STV",
          "Package": "Belintersat",
          "Languages": [
            "rus"
          ],
          "Type": "Unknown",
          "IsFta": false
        },
        {
          "Name": "MIR",
          "Package": "Belintersat",
          "Languages": [
            "rus"
          ],
          "Type": "Unknown",
          "IsFta": false
        },
        {
          "Name": "Rossiya-Belarus",
          "Package": "Belintersat",
          "Languages": [
            "rus"
          ],
          "Type": "Unknown",
          "IsFta": false
        },
        {
          "Name": "NTV-Belarus",
          "Package": "Belintersat",
          "Languages": [
            "rus"
          ],
          "Type": "Unknown",
          "IsFta": false
        },
        {
          "Name": "Belarus 2",
          "Package": "Belintersat",
          "Languages": [
            "rus"
          ],
          "Type": "Unknown",
          "IsFta": false
        },
        {
          "Name": "Belarus 3",
          "Package": "Belintersat",
          "Languages": [
            "rus"
          ],
          "Type": "Unknown",
          "IsFta": false
        },
        {
          "Name": "Belarus 5",
          "Package": "Belintersat",
          "Languages": [
            "rus"
          ],
          "Type": "Unknown",
          "IsFta": false
        },
        {
          "Name": "Pervyj informacionnyj",
          "Package": "Belintersat",
          "Languages": [
            "rus"
          ],
          "Type": "Unknown",
          "IsFta": false
        },
        {
          "Name": "Belintersat Promo",
          "Package": "Belintersat",
          "Languages": [],
          "Type": "TV",
          "IsFta": true
        }
      ]
    },
    {
      "FrequencyMHz": 11387,
      "Polarization": "V",
      "SymbolRateKs": 27500,
      "Fec": "2/3",
      "Standard": "DVB-S",
      "Modulation": "QPSK",
      "Channels": []
    },
    {
      "FrequencyMHz": 11420.8,
      "Polarization": "H",
      "SymbolRateKs": 22000,
      "Fec": "5/6",
      "Standard": "DVB-S",
      "Modulation": "QPSK",
      "Channels": []
    },
    {
      "FrequencyMHz": 11426,
      "Polarization": "V",
      "SymbolRateKs": 20000,
      "Fec": "3/4",
      "Standard": "DVB-S",
      "Modulation": "QPSK",
      "Channels": []
    }
  ]
}